citram_api/__init__.py
citram_api/api/__init__.py
citram_api/api/citram_api_DEPRECATED.py
citram_api/api/lines/__init__.py
citram_api/api/lines/lines.py
citram_api/api/offices/__init__.py
citram_api/api/offices/offices.py
citram_api/api/others/__init__.py
citram_api/api/others/others.py
citram_api/api/stops/__init__.py
citram_api/api/stops/stops.py
citram_api/constants/__init__.py
citram_api/constants/constants.py
citram_api/constants/hosts.py
citram_api/utils/__init__.py
citram_api/utils/custom_exceptions.py
citram_api/utils/utils.py
citram_python_api-1.0.3.dist-info/METADATA
citram_python_api-1.0.3.dist-info/RECORD
citram_python_api-1.0.3.dist-info/WHEEL
citram_python_api-1.0.3.dist-info/top_level.txt
