Metadata-Version: 2.1
Name: citram-python-api
Version: 1.0.3
Summary: Regional Consortium of Transportation for Madrid API wrapper
Home-page: https://github.com/jvicentem/citram-python-api
Author: José Vicente Mellado
Author-email: contact@jvm16.xyz 
License: UNKNOWN
Keywords: madrid transport api
Platform: UNKNOWN
Requires-Python: >=3.6
Requires-Dist: zeep (==3.4.0)
Requires-Dist: xmltodict (==0.12.0)
Requires-Dist: requests (==2.22.0)
